robertcommonsample/__init__.py
robertcommonsample/system/__init__.py
robertcommonsample/system/sample/__init__.py
robertcommonsample/system/sample/dt.py
robertcommonsample/system/sample/os.py
tests/__init__.py
tests/test_system/__init__.py
tests/test_system/test_sample/__init__.py
RobertCommonSample-0.1.1.dist-info/LICENSE
RobertCommonSample-0.1.1.dist-info/METADATA
RobertCommonSample-0.1.1.dist-info/WHEEL
RobertCommonSample-0.1.1.dist-info/top_level.txt
RobertCommonSample-0.1.1.dist-info/RECORD
