Metadata-Version: 2.1
Name: RobertCommonSample
Version: 0.1.1
Summary: Robert Common Sample Library
Home-page: https://github.com/hun0423/RobertCommonSample
Author: Robert0423
Author-email: 851010070@qq.com
License: MIT
Classifier: License :: OSI Approved :: MIT License
Classifier: Programming Language :: Python
Classifier: Programming Language :: Python :: 3
Classifier: Programming Language :: Python :: 3.6
Classifier: Programming Language :: Python :: Implementation :: CPython
Classifier: Programming Language :: Python :: Implementation :: PyPy
Requires-Python: >=3.6.0
License-File: LICENSE
Requires-Dist: python-dateutil
